quantumaudio/__init__.py
quantumaudio/interfaces/api.py
quantumaudio/schemes/__init__.py
quantumaudio/schemes/base_scheme.py
quantumaudio/schemes/mqsm.py
quantumaudio/schemes/msqpam.py
quantumaudio/schemes/qpam.py
quantumaudio/schemes/qsm.py
quantumaudio/schemes/sqpam.py
quantumaudio/tools/__init__.py
quantumaudio/tools/plot.py
quantumaudio/tools/stream.py
quantumaudio/utils/__init__.py
quantumaudio/utils/circuit.py
quantumaudio/utils/convert.py
quantumaudio/utils/data.py
quantumaudio/utils/execute.py
quantumaudio/utils/preview.py
quantumaudio/utils/results.py
quantumaudio-0.2.0.dist-info/licenses/LICENSE
quantumaudio-0.2.0.dist-info/licenses/NOTICE
quantumaudio-0.2.0.dist-info/METADATA
quantumaudio-0.2.0.dist-info/WHEEL
quantumaudio-0.2.0.dist-info/top_level.txt
quantumaudio-0.2.0.dist-info/RECORD
