Metadata-Version: 2.4
Name: quantumaudio
Version: 0.2.0
Summary: A Python package for building Quantum Representations of Digital Audio. Developed by Moth Quantum.
Author-email: Moth Quantum and collaborators <qap.support@mothquantum.com>
License-Expression: Apache-2.0
Project-URL: Homepage, https://mothquantum.com
Project-URL: Repository, https://github.com/moth-quantum/quantum-audio
Project-URL: Documentation, https://quantumaudio.readthedocs.io/
Keywords: audio,quantum computing,signal processing
Classifier: Development Status :: 4 - Beta
Classifier: Intended Audience :: Science/Research
Classifier: Intended Audience :: Developers
Classifier: Programming Language :: Python :: 3.9
Classifier: Programming Language :: Python :: 3.10
Classifier: Programming Language :: Python :: 3.11
Classifier: Programming Language :: Python :: 3.12
Requires-Python: >=3.9
License-File: LICENSE
License-File: NOTICE
Requires-Dist: qiskit
Requires-Dist: qiskit_aer
Requires-Dist: numpy
Requires-Dist: bitstring
Requires-Dist: matplotlib
Requires-Dist: pylatexenc
Requires-Dist: tqdm
Requires-Dist: packaging
Provides-Extra: demos
Requires-Dist: soundfile==0.12.1; extra == "demos"
Requires-Dist: librosa==0.10.2.post1; extra == "demos"
Requires-Dist: ipywidgets; extra == "demos"
Dynamic: license-file
